scripts/__init__.py
scripts/main.py
cash_converter_cli-0.1.1.dist-info/LICENSE
cash_converter_cli-0.1.1.dist-info/METADATA
cash_converter_cli-0.1.1.dist-info/WHEEL
cash_converter_cli-0.1.1.dist-info/entry_points.txt
cash_converter_cli-0.1.1.dist-info/top_level.txt
cash_converter_cli-0.1.1.dist-info/RECORD
