Metadata-Version: 2.1
Name: cash-converter-cli
Version: 0.1.1
Summary: Currency converter using lastest data from fixer.io
Home-page: https://github.com/daenylio/cash-converter-cli
Author: Tuan Nguyen
Author-email: tuan.nguyenviet271@gmail.com
License: UNKNOWN
Platform: UNKNOWN
Classifier: Programming Language :: Python :: 3
Classifier: License :: OSI Approved :: MIT License
Classifier: Operating System :: OS Independent
Requires-Dist: click
